{
  "PersistentObject": {
    "$id": "PersistentObject:9623e408-4b05-35c4-b3df-525e6daa477e",
    "Id": "9623e408-4b05-35c4-b3df-525e6daa477e",
    "SchemaName": "RheaWebsiteLatest",
    "Type": "PortalMain",
    "Salt": "oc9RxHRnITdG12z2pGVRU9O6KwCg-mDE2hCfo3aKaJiaeyRvStGW8g",
    "Breadcrumb": "{PortalPage}",
    "ContextProperty": "PortalMains",
    "Label": {
      "en": "Portal main"
    },
    "Groups": [
      {
        "$id": "PersistentObjectAttributeGroup:6df2683a-5a78-433f-b256-b71996e2b325",
        "Id": "6df2683a-5a78-433f-b256-b71996e2b325"
      }
    ],
    "Tabs": [
      {
        "$id": "PersistentObjectAttributeTab:7d9fea5d-71fb-4659-ae4e-e1ab95cc4ee4",
        "Id": "7d9fea5d-71fb-4659-ae4e-e1ab95cc4ee4"
      }
    ],
    "Attributes": [
      {
        "$id": "PersistentObjectAttribute:5c9996ae-d5a3-38af-9bc5-5f766ad1d483",
        "Id": "5c9996ae-d5a3-38af-9bc5-5f766ad1d483",
        "Offset": 10,
        "Rules": "MaxLength(255)",
        "Name": "ChangedBy",
        "Label": {
          "en": "Changed by"
        },
        "Visibility": 7,
        "ColumnSpan": 1,
        "DataType": {
          "$ref": "DataType:String"
        },
        "Group": {
          "$ref": "PersistentObjectAttributeGroup:6df2683a-5a78-433f-b256-b71996e2b325"
        },
        "Tab": {
          "$ref": "PersistentObjectAttributeTab:7d9fea5d-71fb-4659-ae4e-e1ab95cc4ee4"
        }
      },
      {
        "$id": "PersistentObjectAttribute:bb695bd2-2a31-3e02-a396-f412eb482f75",
        "Id": "bb695bd2-2a31-3e02-a396-f412eb482f75",
        "Offset": 20,
        "Name": "ChangedOn",
        "Label": {
          "en": "Changed on"
        },
        "Visibility": 7,
        "ColumnSpan": 1,
        "DataType": {
          "$ref": "DataType:NullableDateTime"
        },
        "Group": {
          "$ref": "PersistentObjectAttributeGroup:6df2683a-5a78-433f-b256-b71996e2b325"
        },
        "Tab": {
          "$ref": "PersistentObjectAttributeTab:7d9fea5d-71fb-4659-ae4e-e1ab95cc4ee4"
        }
      },
      {
        "$id": "PersistentObjectAttribute:19204e3e-e713-3841-8f69-28746e68d4ee",
        "Id": "19204e3e-e713-3841-8f69-28746e68d4ee",
        "Offset": 30,
        "Rules": "NotEmpty; MaxLength(255)",
        "Name": "CreatedBy",
        "Label": {
          "en": "Created by"
        },
        "Visibility": 7,
        "ColumnSpan": 1,
        "DataType": {
          "$ref": "DataType:String"
        },
        "Group": {
          "$ref": "PersistentObjectAttributeGroup:6df2683a-5a78-433f-b256-b71996e2b325"
        },
        "Tab": {
          "$ref": "PersistentObjectAttributeTab:7d9fea5d-71fb-4659-ae4e-e1ab95cc4ee4"
        }
      },
      {
        "$id": "PersistentObjectAttribute:d4557e33-9e20-3271-b264-f4ba221eaf93",
        "Id": "d4557e33-9e20-3271-b264-f4ba221eaf93",
        "Offset": 40,
        "Rules": "Required",
        "Name": "CreatedOn",
        "Label": {
          "en": "Created on"
        },
        "Visibility": 7,
        "ColumnSpan": 1,
        "DataType": {
          "$ref": "DataType:DateTime"
        },
        "Group": {
          "$ref": "PersistentObjectAttributeGroup:6df2683a-5a78-433f-b256-b71996e2b325"
        },
        "Tab": {
          "$ref": "PersistentObjectAttributeTab:7d9fea5d-71fb-4659-ae4e-e1ab95cc4ee4"
        }
      },
      {
        "$id": "PersistentObjectAttribute:da1d009e-c222-3671-b99b-c690881b47c9",
        "Id": "da1d009e-c222-3671-b99b-c690881b47c9",
        "Offset": 7,
        "Name": "NavSectionHeader",
        "Label": {
          "en": "Nav section header"
        },
        "Visibility": 7,
        "ColumnSpan": 1,
        "DataType": {
          "$ref": "DataType:String"
        },
        "Group": {
          "$ref": "PersistentObjectAttributeGroup:6df2683a-5a78-433f-b256-b71996e2b325"
        },
        "Tab": {
          "$ref": "PersistentObjectAttributeTab:7d9fea5d-71fb-4659-ae4e-e1ab95cc4ee4"
        }
      },
      {
        "$id": "PersistentObjectAttribute:5590859b-31bf-3351-a3cd-0a6cb3b1881f",
        "Id": "5590859b-31bf-3351-a3cd-0a6cb3b1881f",
        "Offset": 8,
        "Name": "NavSectionTitle",
        "Label": {
          "en": "Nav section title"
        },
        "Visibility": 7,
        "ColumnSpan": 1,
        "DataType": {
          "$ref": "DataType:String"
        },
        "Group": {
          "$ref": "PersistentObjectAttributeGroup:6df2683a-5a78-433f-b256-b71996e2b325"
        },
        "Tab": {
          "$ref": "PersistentObjectAttributeTab:7d9fea5d-71fb-4659-ae4e-e1ab95cc4ee4"
        }
      },
      {
        "$id": "PersistentObjectAttributeWithReference:59700a33-70af-3d62-a0fd-e3fbe54b59cf",
        "$type": "Vidyano.Service.Repository.PersistentObjectAttributeWithReference, Vidyano.Service",
        "DisplayAttribute": "Name",
        "LookupId": "e8648841-0234-40f6-b782-5469abb8adb5",
        "Id": "59700a33-70af-3d62-a0fd-e3fbe54b59cf",
        "Offset": 5,
        "Rules": "Required",
        "Name": "PortalPage",
        "Label": {
          "en": "Portal page"
        },
        "Visibility": 7,
        "ColumnSpan": 1,
        "DataType": {
          "$ref": "DataType:Reference"
        },
        "Group": {
          "$ref": "PersistentObjectAttributeGroup:6df2683a-5a78-433f-b256-b71996e2b325"
        },
        "Tab": {
          "$ref": "PersistentObjectAttributeTab:7d9fea5d-71fb-4659-ae4e-e1ab95cc4ee4"
        }
      },
      {
        "$id": "PersistentObjectAttributeWithReference:1524e635-2607-3ce5-9597-be0e96a915cc",
        "$type": "Vidyano.Service.Repository.PersistentObjectAttributeWithReference, Vidyano.Service",
        "DisplayAttribute": "PortalSectionVideo",
        "LookupId": "46c49e4c-c520-428e-aac0-f771693c56d7",
        "Id": "1524e635-2607-3ce5-9597-be0e96a915cc",
        "Offset": 9,
        "Rules": "Required",
        "Name": "PortalVideo",
        "Label": {
          "en": "Portal video"
        },
        "Visibility": 7,
        "ColumnSpan": 1,
        "DataType": {
          "$ref": "DataType:Reference"
        },
        "Group": {
          "$ref": "PersistentObjectAttributeGroup:6df2683a-5a78-433f-b256-b71996e2b325"
        },
        "Tab": {
          "$ref": "PersistentObjectAttributeTab:7d9fea5d-71fb-4659-ae4e-e1ab95cc4ee4"
        }
      }
    ],
    "Queries": []
  },
  "Queries": [
    {
      "$id": "Query:14f6de62-8616-4abc-8198-4dc25316d6fc",
      "Id": "14f6de62-8616-4abc-8198-4dc25316d6fc",
      "Source": "Database.PortalMains",
      "AutoQuery": true,
      "Name": "PortalMains",
      "Label": {
        "en": "Portal mains"
      },
      "PersistentObject": {
        "$ref": "PersistentObject:9623e408-4b05-35c4-b3df-525e6daa477e"
      },
      "Columns": []
    },
    {
      "$id": "Query:d95437d9-d0b4-41a8-8141-1d058df4a0d7",
      "Id": "d95437d9-d0b4-41a8-8141-1d058df4a0d7",
      "Offset": 20,
      "Source": "PortalMains",
      "AutoQuery": true,
      "Name": "PortalPage_PortalMains",
      "Label": {
        "en": "Portal mains"
      },
      "PersistentObject": {
        "$ref": "PersistentObject:9623e408-4b05-35c4-b3df-525e6daa477e"
      },
      "Columns": []
    }
  ],
  "Reports": []
}